tnt/__init__.py
tnt/sparnn.py
tnt_learn-0.0.1.dist-info/METADATA
tnt_learn-0.0.1.dist-info/WHEEL
tnt_learn-0.0.1.dist-info/top_level.txt
tnt_learn-0.0.1.dist-info/RECORD
