Metadata-Version: 2.1
Name: tnt-learn
Version: 0.0.1
Summary: Fast search in text data using cluster-pruning k-nearest neighbor search
Home-page: https://github.com/kerighan/tnt
Author: Maixent Chenebaux
Author-email: max.chbx@gmail.com
License: UNKNOWN
Platform: UNKNOWN
Classifier: Programming Language :: Python :: 3
Classifier: Programming Language :: Python :: 3.7
Classifier: License :: OSI Approved :: MIT License
Classifier: Operating System :: OS Independent
Requires-Dist: scikit-learn
Requires-Dist: dill
Requires-Dist: numpy
Requires-Dist: scipy
Requires-Dist: nearset (>=0.0.4)
Requires-Dist: blist
